[
    {
        "client_msg_id": "774d0971-9813-425a-b674-e0e5082dac37",
        "type": "message",
        "text": "今日までにまとめられた数式などを、Notionを使ってまとめてみました。\n<https:\/\/rhetorical-shield-224.notion.site\/4ad3a46ab3cc4a01b638ea1a5bab81ae>",
        "user": "UKUKA65GU",
        "ts": "1629459587.010700",
        "team": "TKS1Q2JUE",
        "user_team": "TKS1Q2JUE",
        "source_team": "TKS1Q2JUE",
        "user_profile": {
            "avatar_hash": "2ca49c115fb9",
            "image_72": "https:\/\/avatars.slack-edge.com\/2020-08-18\/1300148995014_2ca49c115fb95a7e9654_72.png",
            "first_name": "Sota",
            "real_name": "Sota Chiba",
            "display_name": "sota",
            "team": "TKS1Q2JUE",
            "name": "s1260180",
            "is_restricted": false,
            "is_ultra_restricted": false
        },
        "attachments": [
            {
                "service_name": "Sota Chiba's Notion on Notion",
                "title": "卒業研究・メモ",
                "title_link": "https:\/\/rhetorical-shield-224.notion.site\/4ad3a46ab3cc4a01b638ea1a5bab81ae",
                "text": "(1) タグセットの組み合わせについて",
                "fallback": "Sota Chiba's Notion on Notion: 卒業研究・メモ",
                "from_url": "https:\/\/rhetorical-shield-224.notion.site\/4ad3a46ab3cc4a01b638ea1a5bab81ae",
                "service_icon": "https:\/\/rhetorical-shield-224.notion.site\/images\/favicon.ico",
                "id": 1,
                "original_url": "https:\/\/rhetorical-shield-224.notion.site\/4ad3a46ab3cc4a01b638ea1a5bab81ae"
            }
        ],
        "blocks": [
            {
                "type": "rich_text",
                "block_id": "0TtNV",
                "elements": [
                    {
                        "type": "rich_text_section",
                        "elements": [
                            {
                                "type": "text",
                                "text": "今日までにまとめられた数式などを、Notionを使ってまとめてみました。\n"
                            },
                            {
                                "type": "link",
                                "url": "https:\/\/rhetorical-shield-224.notion.site\/4ad3a46ab3cc4a01b638ea1a5bab81ae"
                            }
                        ]
                    }
                ]
            }
        ],
        "thread_ts": "1629459587.010700",
        "reply_count": 2,
        "reply_users_count": 2,
        "latest_reply": "1630919013.000300",
        "reply_users": [
            "UKS1Q2KTQ",
            "UKUKA65GU"
        ],
        "replies": [
            {
                "user": "UKS1Q2KTQ",
                "ts": "1630878274.000100"
            },
            {
                "user": "UKUKA65GU",
                "ts": "1630919013.000300"
            }
        ],
        "is_locked": false,
        "subscribed": true,
        "last_read": "1630919013.000300",
        "reactions": [
            {
                "name": "+1",
                "users": [
                    "UQ47R82RW"
                ],
                "count": 1
            }
        ]
    }
]