[
    {
        "client_msg_id": "A482B7E0-A893-4409-A706-A02D52BDCE90",
        "type": "message",
        "text": "一応データは作成できて、可視化までいけたのですが、やはり数字で比較をせずに出力するだけでは違いが分かりませんでした\n以下スレッドに動画を貼ります",
        "user": "UKH07E67M",
        "ts": "1595066389.127700",
        "team": "TKS1Q2JUE",
        "user_team": "TKS1Q2JUE",
        "source_team": "TKS1Q2JUE",
        "user_profile": {
            "avatar_hash": "42b0524c15ef",
            "image_72": "https:\/\/avatars.slack-edge.com\/2020-12-22\/1589400144565_42b0524c15efa13345bf_72.png",
            "first_name": "Aoshi",
            "real_name": "Aoshi Suzuki",
            "display_name": "aoshi",
            "team": "TKS1Q2JUE",
            "name": "s1260241",
            "is_restricted": false,
            "is_ultra_restricted": false
        },
        "edited": {
            "user": "UKH07E67M",
            "ts": "1595066464.000000"
        },
        "blocks": [
            {
                "type": "rich_text",
                "block_id": "ilcA",
                "elements": [
                    {
                        "type": "rich_text_section",
                        "elements": [
                            {
                                "type": "text",
                                "text": "一応データは作成できて、可視化までいけたのですが、やはり数字で比較をせずに出力するだけでは違いが分かりませんでした\n以下スレッドに動画を貼ります"
                            }
                        ]
                    }
                ]
            }
        ],
        "thread_ts": "1595066389.127700",
        "reply_count": 9,
        "reply_users_count": 2,
        "latest_reply": "1595068414.132000",
        "reply_users": [
            "UKH07E67M",
            "UKS1Q2KTQ"
        ],
        "replies": [
            {
                "user": "UKH07E67M",
                "ts": "1595066677.128900"
            },
            {
                "user": "UKH07E67M",
                "ts": "1595066699.129300"
            },
            {
                "user": "UKH07E67M",
                "ts": "1595066727.129700"
            },
            {
                "user": "UKH07E67M",
                "ts": "1595066750.130100"
            },
            {
                "user": "UKH07E67M",
                "ts": "1595066840.130500"
            },
            {
                "user": "UKS1Q2KTQ",
                "ts": "1595067563.130700"
            },
            {
                "user": "UKS1Q2KTQ",
                "ts": "1595067730.130900"
            },
            {
                "user": "UKH07E67M",
                "ts": "1595068076.131800"
            },
            {
                "user": "UKS1Q2KTQ",
                "ts": "1595068414.132000"
            }
        ],
        "is_locked": false,
        "subscribed": true,
        "last_read": "1595068414.132000",
        "reactions": [
            {
                "name": "+1",
                "users": [
                    "UPSPAP97D"
                ],
                "count": 1
            }
        ]
    },
    {
        "type": "message",
        "text": "201902 非活動時間",
        "files": [
            {
                "id": "F017PTB5Z41",
                "created": 1595066659,
                "timestamp": 1595066659,
                "name": "616759399.399597.mp4",
                "title": "616759399.399597.mp4",
                "mimetype": "video\/mp4",
                "filetype": "mp4",
                "pretty_type": "MPEG 4 Video",
                "user": "UKH07E67M",
                "editable": false,
                "size": 1444165,
                "mode": "hosted",
                "is_external": false,
                "external_type": "",
                "is_public": true,
                "public_url_shared": false,
                "display_as_bot": false,
                "username": "",
                "url_private": "https:\/\/files.slack.com\/files-pri\/TKS1Q2JUE-F017PTB5Z41\/616759399.399597.mp4?t=xoxe-672058086966-2523672994084-2517456103667-564347be5337331371fc88513b8caa70",
                "url_private_download": "https:\/\/files.slack.com\/files-pri\/TKS1Q2JUE-F017PTB5Z41\/download\/616759399.399597.mp4?t=xoxe-672058086966-2523672994084-2517456103667-564347be5337331371fc88513b8caa70",
                "media_display_type": "video",
                "thumb_video": "https:\/\/files.slack.com\/files-tmb\/TKS1Q2JUE-F017PTB5Z41-d48927c96a\/616759399.399597_thumb_video.jpeg?t=xoxe-672058086966-2523672994084-2517456103667-564347be5337331371fc88513b8caa70",
                "permalink": "https:\/\/css-uoa.slack.com\/files\/UKH07E67M\/F017PTB5Z41\/616759399.399597.mp4",
                "permalink_public": "https:\/\/slack-files.com\/TKS1Q2JUE-F017PTB5Z41-91b080ee7e",
                "is_starred": false,
                "has_rich_preview": false
            }
        ],
        "upload": false,
        "blocks": [
            {
                "type": "rich_text",
                "block_id": "fcp5c",
                "elements": [
                    {
                        "type": "rich_text_section",
                        "elements": [
                            {
                                "type": "text",
                                "text": "201902 非活動時間"
                            }
                        ]
                    }
                ]
            }
        ],
        "user": "UKH07E67M",
        "display_as_bot": false,
        "ts": "1595066677.128900",
        "thread_ts": "1595066389.127700",
        "parent_user_id": "UKH07E67M"
    },
    {
        "type": "message",
        "text": "同日活動時間",
        "files": [
            {
                "id": "F018148RPBJ",
                "created": 1595066685,
                "timestamp": 1595066685,
                "name": "616759399.549859.mp4",
                "title": "616759399.549859.mp4",
                "mimetype": "video\/mp4",
                "filetype": "mp4",
                "pretty_type": "MPEG 4 Video",
                "user": "UKH07E67M",
                "editable": false,
                "size": 1434991,
                "mode": "hosted",
                "is_external": false,
                "external_type": "",
                "is_public": true,
                "public_url_shared": false,
                "display_as_bot": false,
                "username": "",
                "url_private": "https:\/\/files.slack.com\/files-pri\/TKS1Q2JUE-F018148RPBJ\/616759399.549859.mp4?t=xoxe-672058086966-2523672994084-2517456103667-564347be5337331371fc88513b8caa70",
                "url_private_download": "https:\/\/files.slack.com\/files-pri\/TKS1Q2JUE-F018148RPBJ\/download\/616759399.549859.mp4?t=xoxe-672058086966-2523672994084-2517456103667-564347be5337331371fc88513b8caa70",
                "media_display_type": "video",
                "thumb_video": "https:\/\/files.slack.com\/files-tmb\/TKS1Q2JUE-F018148RPBJ-0298c82ff9\/616759399.549859_thumb_video.jpeg?t=xoxe-672058086966-2523672994084-2517456103667-564347be5337331371fc88513b8caa70",
                "permalink": "https:\/\/css-uoa.slack.com\/files\/UKH07E67M\/F018148RPBJ\/616759399.549859.mp4",
                "permalink_public": "https:\/\/slack-files.com\/TKS1Q2JUE-F018148RPBJ-2e1e31d27c",
                "is_starred": false,
                "has_rich_preview": false
            }
        ],
        "upload": false,
        "blocks": [
            {
                "type": "rich_text",
                "block_id": "NJNXf",
                "elements": [
                    {
                        "type": "rich_text_section",
                        "elements": [
                            {
                                "type": "text",
                                "text": "同日活動時間"
                            }
                        ]
                    }
                ]
            }
        ],
        "user": "UKH07E67M",
        "display_as_bot": false,
        "ts": "1595066699.129300",
        "thread_ts": "1595066389.127700",
        "parent_user_id": "UKH07E67M"
    },
    {
        "type": "message",
        "text": "同日活動時間　会津若松市民",
        "files": [
            {
                "id": "F0181490R6U",
                "created": 1595066706,
                "timestamp": 1595066706,
                "name": "616759399.649849.mp4",
                "title": "616759399.649849.mp4",
                "mimetype": "video\/mp4",
                "filetype": "mp4",
                "pretty_type": "MPEG 4 Video",
                "user": "UKH07E67M",
                "editable": false,
                "size": 1768854,
                "mode": "hosted",
                "is_external": false,
                "external_type": "",
                "is_public": true,
                "public_url_shared": false,
                "display_as_bot": false,
                "username": "",
                "url_private": "https:\/\/files.slack.com\/files-pri\/TKS1Q2JUE-F0181490R6U\/616759399.649849.mp4?t=xoxe-672058086966-2523672994084-2517456103667-564347be5337331371fc88513b8caa70",
                "url_private_download": "https:\/\/files.slack.com\/files-pri\/TKS1Q2JUE-F0181490R6U\/download\/616759399.649849.mp4?t=xoxe-672058086966-2523672994084-2517456103667-564347be5337331371fc88513b8caa70",
                "media_display_type": "video",
                "thumb_video": "https:\/\/files.slack.com\/files-tmb\/TKS1Q2JUE-F0181490R6U-a930df0754\/616759399.649849_thumb_video.jpeg?t=xoxe-672058086966-2523672994084-2517456103667-564347be5337331371fc88513b8caa70",
                "permalink": "https:\/\/css-uoa.slack.com\/files\/UKH07E67M\/F0181490R6U\/616759399.649849.mp4",
                "permalink_public": "https:\/\/slack-files.com\/TKS1Q2JUE-F0181490R6U-3a8766fa16",
                "is_starred": false,
                "has_rich_preview": false
            }
        ],
        "upload": false,
        "blocks": [
            {
                "type": "rich_text",
                "block_id": "lzH\/Y",
                "elements": [
                    {
                        "type": "rich_text_section",
                        "elements": [
                            {
                                "type": "text",
                                "text": "同日活動時間　会津若松市民"
                            }
                        ]
                    }
                ]
            }
        ],
        "user": "UKH07E67M",
        "display_as_bot": false,
        "ts": "1595066727.129700",
        "thread_ts": "1595066389.127700",
        "parent_user_id": "UKH07E67M"
    },
    {
        "type": "message",
        "text": "同日活動時間　県内、県外の方",
        "files": [
            {
                "id": "F017PTBNGJV",
                "created": 1595066732,
                "timestamp": 1595066732,
                "name": "616759399.730116.mp4",
                "title": "616759399.730116.mp4",
                "mimetype": "video\/mp4",
                "filetype": "mp4",
                "pretty_type": "MPEG 4 Video",
                "user": "UKH07E67M",
                "editable": false,
                "size": 1726577,
                "mode": "hosted",
                "is_external": false,
                "external_type": "",
                "is_public": true,
                "public_url_shared": false,
                "display_as_bot": false,
                "username": "",
                "url_private": "https:\/\/files.slack.com\/files-pri\/TKS1Q2JUE-F017PTBNGJV\/616759399.730116.mp4?t=xoxe-672058086966-2523672994084-2517456103667-564347be5337331371fc88513b8caa70",
                "url_private_download": "https:\/\/files.slack.com\/files-pri\/TKS1Q2JUE-F017PTBNGJV\/download\/616759399.730116.mp4?t=xoxe-672058086966-2523672994084-2517456103667-564347be5337331371fc88513b8caa70",
                "media_display_type": "video",
                "thumb_video": "https:\/\/files.slack.com\/files-tmb\/TKS1Q2JUE-F017PTBNGJV-643578951a\/616759399.730116_thumb_video.jpeg?t=xoxe-672058086966-2523672994084-2517456103667-564347be5337331371fc88513b8caa70",
                "permalink": "https:\/\/css-uoa.slack.com\/files\/UKH07E67M\/F017PTBNGJV\/616759399.730116.mp4",
                "permalink_public": "https:\/\/slack-files.com\/TKS1Q2JUE-F017PTBNGJV-1bbba6b7f5",
                "is_starred": false,
                "has_rich_preview": false
            }
        ],
        "upload": false,
        "blocks": [
            {
                "type": "rich_text",
                "block_id": "Gjd",
                "elements": [
                    {
                        "type": "rich_text_section",
                        "elements": [
                            {
                                "type": "text",
                                "text": "同日活動時間　県内、県外の方"
                            }
                        ]
                    }
                ]
            }
        ],
        "user": "UKH07E67M",
        "display_as_bot": false,
        "ts": "1595066750.130100",
        "thread_ts": "1595066389.127700",
        "parent_user_id": "UKH07E67M"
    },
    {
        "client_msg_id": "0cfc3b1e-5961-4591-81de-1cd6ea16a510",
        "type": "message",
        "text": "サークルの大きさはそのメッシュに当たるデータの数に比例して大きくなります。\n\nただ、これ見ても何もわからないので、自分のアイデアをマシにするには、数字で比較して厳選したものを出力しないとダメだと思っています。",
        "user": "UKH07E67M",
        "ts": "1595066840.130500",
        "team": "TKS1Q2JUE",
        "user_team": "TKS1Q2JUE",
        "source_team": "TKS1Q2JUE",
        "user_profile": {
            "avatar_hash": "42b0524c15ef",
            "image_72": "https:\/\/avatars.slack-edge.com\/2020-12-22\/1589400144565_42b0524c15efa13345bf_72.png",
            "first_name": "Aoshi",
            "real_name": "Aoshi Suzuki",
            "display_name": "aoshi",
            "team": "TKS1Q2JUE",
            "name": "s1260241",
            "is_restricted": false,
            "is_ultra_restricted": false
        },
        "blocks": [
            {
                "type": "rich_text",
                "block_id": "59Q",
                "elements": [
                    {
                        "type": "rich_text_section",
                        "elements": [
                            {
                                "type": "text",
                                "text": "サークルの大きさはそのメッシュに当たるデータの数に比例して大きくなります。\n\nただ、これ見ても何もわからないので、自分のアイデアをマシにするには、数字で比較して厳選したものを出力しないとダメだと思っています。"
                            }
                        ]
                    }
                ]
            }
        ],
        "thread_ts": "1595066389.127700",
        "parent_user_id": "UKH07E67M"
    },
    {
        "client_msg_id": "be1e4255-fd79-4368-843e-e9bebf6f7490",
        "type": "message",
        "text": "<@UKH07E67M> アニメーションにする必要はなくて、会津若松市民とそれ以外について、2019昼、2019夜、2020昼、2020夜の4枚（計8枚）の絵を出して、並べてみると、違いは出るんじゃないかな？",
        "user": "UKS1Q2KTQ",
        "ts": "1595067563.130700",
        "team": "TKS1Q2JUE",
        "user_team": "TKS1Q2JUE",
        "source_team": "TKS1Q2JUE",
        "user_profile": {
            "avatar_hash": "g2cdaa6f0a3e",
            "image_72": "https:\/\/secure.gravatar.com\/avatar\/72cdaa6f0a3e75d134cc6b97d821b078.jpg?s=72&d=https%3A%2F%2Fa.slack-edge.com%2Fdf10d%2Fimg%2Favatars%2Fava_0003-72.png",
            "first_name": "Yasuhiro",
            "real_name": "Yasuhiro Hashimoto",
            "display_name": "hashimoto",
            "team": "TKS1Q2JUE",
            "name": "yasuhirohashimoto",
            "is_restricted": false,
            "is_ultra_restricted": false
        },
        "blocks": [
            {
                "type": "rich_text",
                "block_id": "tX=ac",
                "elements": [
                    {
                        "type": "rich_text_section",
                        "elements": [
                            {
                                "type": "user",
                                "user_id": "UKH07E67M"
                            },
                            {
                                "type": "text",
                                "text": " アニメーションにする必要はなくて、会津若松市民とそれ以外について、2019昼、2019夜、2020昼、2020夜の4枚（計8枚）の絵を出して、並べてみると、違いは出るんじゃないかな？"
                            }
                        ]
                    }
                ]
            }
        ],
        "thread_ts": "1595066389.127700",
        "parent_user_id": "UKH07E67M"
    },
    {
        "client_msg_id": "c6740a24-2f12-40f8-aaf2-0ce590957535",
        "type": "message",
        "text": "<@UKH07E67M> その上でアニメーションを眺めた方がよいので、アニメーションもとっておいた方がいいですね。",
        "user": "UKS1Q2KTQ",
        "ts": "1595067730.130900",
        "team": "TKS1Q2JUE",
        "user_team": "TKS1Q2JUE",
        "source_team": "TKS1Q2JUE",
        "user_profile": {
            "avatar_hash": "g2cdaa6f0a3e",
            "image_72": "https:\/\/secure.gravatar.com\/avatar\/72cdaa6f0a3e75d134cc6b97d821b078.jpg?s=72&d=https%3A%2F%2Fa.slack-edge.com%2Fdf10d%2Fimg%2Favatars%2Fava_0003-72.png",
            "first_name": "Yasuhiro",
            "real_name": "Yasuhiro Hashimoto",
            "display_name": "hashimoto",
            "team": "TKS1Q2JUE",
            "name": "yasuhirohashimoto",
            "is_restricted": false,
            "is_ultra_restricted": false
        },
        "blocks": [
            {
                "type": "rich_text",
                "block_id": "btr5",
                "elements": [
                    {
                        "type": "rich_text_section",
                        "elements": [
                            {
                                "type": "user",
                                "user_id": "UKH07E67M"
                            },
                            {
                                "type": "text",
                                "text": " その上でアニメーションを眺めた方がよいので、アニメーションもとっておいた方がいいですね。"
                            }
                        ]
                    }
                ]
            }
        ],
        "thread_ts": "1595066389.127700",
        "parent_user_id": "UKH07E67M"
    },
    {
        "client_msg_id": "AED78B09-F7FD-4C81-8790-6C3E9E1599FF",
        "type": "message",
        "text": "なるほど、現状の結果としてそれを作っておきます",
        "user": "UKH07E67M",
        "ts": "1595068076.131800",
        "team": "TKS1Q2JUE",
        "user_team": "TKS1Q2JUE",
        "source_team": "TKS1Q2JUE",
        "user_profile": {
            "avatar_hash": "42b0524c15ef",
            "image_72": "https:\/\/avatars.slack-edge.com\/2020-12-22\/1589400144565_42b0524c15efa13345bf_72.png",
            "first_name": "Aoshi",
            "real_name": "Aoshi Suzuki",
            "display_name": "aoshi",
            "team": "TKS1Q2JUE",
            "name": "s1260241",
            "is_restricted": false,
            "is_ultra_restricted": false
        },
        "blocks": [
            {
                "type": "rich_text",
                "block_id": "yzEP",
                "elements": [
                    {
                        "type": "rich_text_section",
                        "elements": [
                            {
                                "type": "text",
                                "text": "なるほど、現状の結果としてそれを作っておきます"
                            }
                        ]
                    }
                ]
            }
        ],
        "thread_ts": "1595066389.127700",
        "parent_user_id": "UKH07E67M"
    },
    {
        "client_msg_id": "61de01cd-bd84-42d4-a3d4-19a595b03116",
        "type": "message",
        "text": "<@UKH07E67M> 篠田さんのコメントでは、動きが見えるといいかも、と仰ってましたね（例えば東山温泉から鶴ヶ城、とか）。だとすると、今回アニメーションを作った方法で、会津若松市民とそれ以外に分けるのはそのままで、昼と夜を分けずに、例えば朝8時から夜8時までのアニメーションにしてもいいかもですね（どうせアニメーションにするなら）。",
        "user": "UKS1Q2KTQ",
        "ts": "1595068414.132000",
        "team": "TKS1Q2JUE",
        "user_team": "TKS1Q2JUE",
        "source_team": "TKS1Q2JUE",
        "user_profile": {
            "avatar_hash": "g2cdaa6f0a3e",
            "image_72": "https:\/\/secure.gravatar.com\/avatar\/72cdaa6f0a3e75d134cc6b97d821b078.jpg?s=72&d=https%3A%2F%2Fa.slack-edge.com%2Fdf10d%2Fimg%2Favatars%2Fava_0003-72.png",
            "first_name": "Yasuhiro",
            "real_name": "Yasuhiro Hashimoto",
            "display_name": "hashimoto",
            "team": "TKS1Q2JUE",
            "name": "yasuhirohashimoto",
            "is_restricted": false,
            "is_ultra_restricted": false
        },
        "edited": {
            "user": "UKS1Q2KTQ",
            "ts": "1595068454.000000"
        },
        "blocks": [
            {
                "type": "rich_text",
                "block_id": "1ne2",
                "elements": [
                    {
                        "type": "rich_text_section",
                        "elements": [
                            {
                                "type": "user",
                                "user_id": "UKH07E67M"
                            },
                            {
                                "type": "text",
                                "text": " 篠田さんのコメントでは、動きが見えるといいかも、と仰ってましたね（例えば東山温泉から鶴ヶ城、とか）。だとすると、今回アニメーションを作った方法で、会津若松市民とそれ以外に分けるのはそのままで、昼と夜を分けずに、例えば朝8時から夜8時までのアニメーションにしてもいいかもですね（どうせアニメーションにするなら）。"
                            }
                        ]
                    }
                ]
            }
        ],
        "thread_ts": "1595066389.127700",
        "parent_user_id": "UKH07E67M",
        "reactions": [
            {
                "name": "man-bowing",
                "users": [
                    "UKH07E67M"
                ],
                "count": 1
            }
        ]
    },
    {
        "type": "message",
        "text": "<@UKS1Q2KTQ> jsonのエラーは、’とプロパティに日本語が含まれていたのが問題でした。現在はプロットは出来るようになりました\n。今は本番用データを用意してます。",
        "files": [
            {
                "id": "F017BQJLF7U",
                "created": 1595140413,
                "timestamp": 1595140413,
                "name": "スクリーンショット 2020-07-19 15.33.24.png",
                "title": "スクリーンショット 2020-07-19 15.33.24.png",
                "mimetype": "image\/png",
                "filetype": "png",
                "pretty_type": "PNG",
                "user": "UPRE1RSJW",
                "editable": false,
                "size": 528725,
                "mode": "hosted",
                "is_external": false,
                "external_type": "",
                "is_public": true,
                "public_url_shared": false,
                "display_as_bot": false,
                "username": "",
                "url_private": "https:\/\/files.slack.com\/files-pri\/TKS1Q2JUE-F017BQJLF7U\/____________________________2020-07-19_15.33.24.png?t=xoxe-672058086966-2523672994084-2517456103667-564347be5337331371fc88513b8caa70",
                "url_private_download": "https:\/\/files.slack.com\/files-pri\/TKS1Q2JUE-F017BQJLF7U\/download\/____________________________2020-07-19_15.33.24.png?t=xoxe-672058086966-2523672994084-2517456103667-564347be5337331371fc88513b8caa70",
                "media_display_type": "unknown",
                "thumb_64": "https:\/\/files.slack.com\/files-tmb\/TKS1Q2JUE-F017BQJLF7U-3dd1a8b83e\/____________________________2020-07-19_15.33.24_64.png?t=xoxe-672058086966-2523672994084-2517456103667-564347be5337331371fc88513b8caa70",
                "thumb_80": "https:\/\/files.slack.com\/files-tmb\/TKS1Q2JUE-F017BQJLF7U-3dd1a8b83e\/____________________________2020-07-19_15.33.24_80.png?t=xoxe-672058086966-2523672994084-2517456103667-564347be5337331371fc88513b8caa70",
                "thumb_360": "https:\/\/files.slack.com\/files-tmb\/TKS1Q2JUE-F017BQJLF7U-3dd1a8b83e\/____________________________2020-07-19_15.33.24_360.png?t=xoxe-672058086966-2523672994084-2517456103667-564347be5337331371fc88513b8caa70",
                "thumb_360_w": 360,
                "thumb_360_h": 211,
                "thumb_480": "https:\/\/files.slack.com\/files-tmb\/TKS1Q2JUE-F017BQJLF7U-3dd1a8b83e\/____________________________2020-07-19_15.33.24_480.png?t=xoxe-672058086966-2523672994084-2517456103667-564347be5337331371fc88513b8caa70",
                "thumb_480_w": 480,
                "thumb_480_h": 282,
                "thumb_160": "https:\/\/files.slack.com\/files-tmb\/TKS1Q2JUE-F017BQJLF7U-3dd1a8b83e\/____________________________2020-07-19_15.33.24_160.png?t=xoxe-672058086966-2523672994084-2517456103667-564347be5337331371fc88513b8caa70",
                "thumb_720": "https:\/\/files.slack.com\/files-tmb\/TKS1Q2JUE-F017BQJLF7U-3dd1a8b83e\/____________________________2020-07-19_15.33.24_720.png?t=xoxe-672058086966-2523672994084-2517456103667-564347be5337331371fc88513b8caa70",
                "thumb_720_w": 720,
                "thumb_720_h": 423,
                "thumb_800": "https:\/\/files.slack.com\/files-tmb\/TKS1Q2JUE-F017BQJLF7U-3dd1a8b83e\/____________________________2020-07-19_15.33.24_800.png?t=xoxe-672058086966-2523672994084-2517456103667-564347be5337331371fc88513b8caa70",
                "thumb_800_w": 800,
                "thumb_800_h": 470,
                "thumb_960": "https:\/\/files.slack.com\/files-tmb\/TKS1Q2JUE-F017BQJLF7U-3dd1a8b83e\/____________________________2020-07-19_15.33.24_960.png?t=xoxe-672058086966-2523672994084-2517456103667-564347be5337331371fc88513b8caa70",
                "thumb_960_w": 960,
                "thumb_960_h": 564,
                "thumb_1024": "https:\/\/files.slack.com\/files-tmb\/TKS1Q2JUE-F017BQJLF7U-3dd1a8b83e\/____________________________2020-07-19_15.33.24_1024.png?t=xoxe-672058086966-2523672994084-2517456103667-564347be5337331371fc88513b8caa70",
                "thumb_1024_w": 1024,
                "thumb_1024_h": 602,
                "original_w": 1818,
                "original_h": 1068,
                "thumb_tiny": "AwAcADDOpVUscAUlPR9vHY0xMkWAFcnPXrTZICnQ5FPjlJBX3zTy+ce1CE5IrFSKbU7rlfl5qA0AncKKKKBlm2KKhJxnPOfSkbHLDpVel3HGM8UA9SXeB3qEnJJoooElY\/\/Z",
                "permalink": "https:\/\/css-uoa.slack.com\/files\/UPRE1RSJW\/F017BQJLF7U\/____________________________2020-07-19_15.33.24.png",
                "permalink_public": "https:\/\/slack-files.com\/TKS1Q2JUE-F017BQJLF7U-0f7c433bcc",
                "is_starred": false,
                "has_rich_preview": false
            }
        ],
        "upload": false,
        "blocks": [
            {
                "type": "rich_text",
                "block_id": "0aV",
                "elements": [
                    {
                        "type": "rich_text_section",
                        "elements": [
                            {
                                "type": "user",
                                "user_id": "UKS1Q2KTQ"
                            },
                            {
                                "type": "text",
                                "text": " jsonのエラーは、’とプロパティに日本語が含まれていたのが問題でした。現在はプロットは出来るようになりました\n。今は本番用データを用意してます。"
                            }
                        ]
                    }
                ]
            }
        ],
        "user": "UPRE1RSJW",
        "display_as_bot": false,
        "ts": "1595140574.134700",
        "thread_ts": "1595140574.134700",
        "reply_count": 10,
        "reply_users_count": 3,
        "latest_reply": "1595151061.139100",
        "reply_users": [
            "UKS1Q2KTQ",
            "UKH07E67M",
            "UPRE1RSJW"
        ],
        "replies": [
            {
                "user": "UKS1Q2KTQ",
                "ts": "1595141460.135000"
            },
            {
                "user": "UKS1Q2KTQ",
                "ts": "1595141620.135200"
            },
            {
                "user": "UKH07E67M",
                "ts": "1595146536.135800"
            },
            {
                "user": "UPRE1RSJW",
                "ts": "1595146580.136500"
            },
            {
                "user": "UPRE1RSJW",
                "ts": "1595146975.136700"
            },
            {
                "user": "UKH07E67M",
                "ts": "1595147125.137400"
            },
            {
                "user": "UKH07E67M",
                "ts": "1595150476.137700"
            },
            {
                "user": "UPRE1RSJW",
                "ts": "1595150546.138100"
            },
            {
                "user": "UPRE1RSJW",
                "ts": "1595150629.138600"
            },
            {
                "user": "UPRE1RSJW",
                "ts": "1595151061.139100"
            }
        ],
        "is_locked": false,
        "subscribed": true,
        "last_read": "1595151061.139100",
        "reactions": [
            {
                "name": "+1",
                "users": [
                    "UPSPAMY7M",
                    "UPSPAP97D",
                    "UQ47R82RW"
                ],
                "count": 3
            }
        ]
    },
    {
        "client_msg_id": "a7cec3f4-1e6a-4b33-ae20-002daa0d7ce9",
        "type": "message",
        "text": "<@UPRE1RSJW> なるほど。ご苦労様。見栄えが一段よくなったね！",
        "user": "UKS1Q2KTQ",
        "ts": "1595141460.135000",
        "team": "TKS1Q2JUE",
        "user_team": "TKS1Q2JUE",
        "source_team": "TKS1Q2JUE",
        "user_profile": {
            "avatar_hash": "g2cdaa6f0a3e",
            "image_72": "https:\/\/secure.gravatar.com\/avatar\/72cdaa6f0a3e75d134cc6b97d821b078.jpg?s=72&d=https%3A%2F%2Fa.slack-edge.com%2Fdf10d%2Fimg%2Favatars%2Fava_0003-72.png",
            "first_name": "Yasuhiro",
            "real_name": "Yasuhiro Hashimoto",
            "display_name": "hashimoto",
            "team": "TKS1Q2JUE",
            "name": "yasuhirohashimoto",
            "is_restricted": false,
            "is_ultra_restricted": false
        },
        "blocks": [
            {
                "type": "rich_text",
                "block_id": "hGXVP",
                "elements": [
                    {
                        "type": "rich_text_section",
                        "elements": [
                            {
                                "type": "user",
                                "user_id": "UPRE1RSJW"
                            },
                            {
                                "type": "text",
                                "text": " なるほど。ご苦労様。見栄えが一段よくなったね！"
                            }
                        ]
                    }
                ]
            }
        ],
        "thread_ts": "1595140574.134700",
        "parent_user_id": "UPRE1RSJW"
    },
    {
        "client_msg_id": "31a994d5-11e9-4e80-b8b0-dae94a0a9ed2",
        "type": "message",
        "text": "情報量としては50mほどの細かいレギュラーメッシュで切ってポリゴンにした方がよいかもだね。こちらの自治体単位はこれはこれでよい可視化だと思うが。",
        "user": "UKS1Q2KTQ",
        "ts": "1595141620.135200",
        "team": "TKS1Q2JUE",
        "user_team": "TKS1Q2JUE",
        "source_team": "TKS1Q2JUE",
        "user_profile": {
            "avatar_hash": "g2cdaa6f0a3e",
            "image_72": "https:\/\/secure.gravatar.com\/avatar\/72cdaa6f0a3e75d134cc6b97d821b078.jpg?s=72&d=https%3A%2F%2Fa.slack-edge.com%2Fdf10d%2Fimg%2Favatars%2Fava_0003-72.png",
            "first_name": "Yasuhiro",
            "real_name": "Yasuhiro Hashimoto",
            "display_name": "hashimoto",
            "team": "TKS1Q2JUE",
            "name": "yasuhirohashimoto",
            "is_restricted": false,
            "is_ultra_restricted": false
        },
        "blocks": [
            {
                "type": "rich_text",
                "block_id": "5P0A",
                "elements": [
                    {
                        "type": "rich_text_section",
                        "elements": [
                            {
                                "type": "text",
                                "text": "情報量としては50mほどの細かいレギュラーメッシュで切ってポリゴンにした方がよいかもだね。こちらの自治体単位はこれはこれでよい可視化だと思うが。"
                            }
                        ]
                    }
                ]
            }
        ],
        "thread_ts": "1595140574.134700",
        "parent_user_id": "UPRE1RSJW",
        "reactions": [
            {
                "name": "heavy_check_mark",
                "users": [
                    "UPRE1RSJW"
                ],
                "count": 1
            }
        ]
    }
]