[
    {
        "client_msg_id": "E8358484-800E-4B5D-BA6B-FB31E9D539C1",
        "type": "message",
        "text": "<@UPRE1RSJW> \n助川さん誕生日おめでとうございます:confetti_ball::tada::birthday:",
        "user": "U01EVRBP38C",
        "ts": "1618363887.044300",
        "team": "TKS1Q2JUE",
        "user_team": "TKS1Q2JUE",
        "source_team": "TKS1Q2JUE",
        "user_profile": {
            "avatar_hash": "1d491b4b6d33",
            "image_72": "https:\/\/avatars.slack-edge.com\/2020-11-14\/1513053597985_1d491b4b6d33b99610d3_72.png",
            "first_name": "Masashi",
            "real_name": "Masashi Sakurai",
            "display_name": "sakurai",
            "team": "TKS1Q2JUE",
            "name": "s12701350406",
            "is_restricted": false,
            "is_ultra_restricted": false
        },
        "blocks": [
            {
                "type": "rich_text",
                "block_id": "vaH",
                "elements": [
                    {
                        "type": "rich_text_section",
                        "elements": [
                            {
                                "type": "user",
                                "user_id": "UPRE1RSJW"
                            },
                            {
                                "type": "text",
                                "text": " \n助川さん誕生日おめでとうございます"
                            },
                            {
                                "type": "emoji",
                                "name": "confetti_ball"
                            },
                            {
                                "type": "emoji",
                                "name": "tada"
                            },
                            {
                                "type": "emoji",
                                "name": "birthday"
                            }
                        ]
                    }
                ]
            }
        ],
        "thread_ts": "1618363887.044300",
        "reply_count": 2,
        "reply_users_count": 2,
        "latest_reply": "1618368350.045400",
        "reply_users": [
            "UQ47R82RW",
            "UPRE1RSJW"
        ],
        "replies": [
            {
                "user": "UQ47R82RW",
                "ts": "1618367193.045100"
            },
            {
                "user": "UPRE1RSJW",
                "ts": "1618368350.045400"
            }
        ],
        "is_locked": false,
        "subscribed": false,
        "reactions": [
            {
                "name": "confetti_ball",
                "users": [
                    "U01EP8BUKQT",
                    "U01EPKVACEN",
                    "U01FP2RDV44",
                    "UKS1Q2KTQ",
                    "UKH07E67M",
                    "UQ47R82RW",
                    "UKUKA65GU",
                    "UPSPAP97D"
                ],
                "count": 8
            }
        ]
    },
    {
        "client_msg_id": "0d84d6fc-13f9-41c3-808c-c7f4ef45a9aa",
        "type": "message",
        "text": "<@UPRE1RSJW> \nおめでとー:tada:",
        "user": "UQ47R82RW",
        "ts": "1618367193.045100",
        "team": "TKS1Q2JUE",
        "user_team": "TKS1Q2JUE",
        "source_team": "TKS1Q2JUE",
        "user_profile": {
            "avatar_hash": "4caf2ceee850",
            "image_72": "https:\/\/avatars.slack-edge.com\/2019-11-08\/813786533666_4caf2ceee850b8dc5dad_72.png",
            "first_name": "kota",
            "real_name": "kota sanuki",
            "display_name": "kota",
            "team": "TKS1Q2JUE",
            "name": "s1260073",
            "is_restricted": false,
            "is_ultra_restricted": false
        },
        "blocks": [
            {
                "type": "rich_text",
                "block_id": "sN85Y",
                "elements": [
                    {
                        "type": "rich_text_section",
                        "elements": [
                            {
                                "type": "user",
                                "user_id": "UPRE1RSJW"
                            },
                            {
                                "type": "text",
                                "text": " \nおめでとー"
                            },
                            {
                                "type": "emoji",
                                "name": "tada"
                            }
                        ]
                    }
                ]
            }
        ],
        "thread_ts": "1618363887.044300",
        "parent_user_id": "U01EVRBP38C"
    },
    {
        "client_msg_id": "01c4570d-b128-46ff-ba07-e65c8438685b",
        "type": "message",
        "text": "ありがとー",
        "user": "UPRE1RSJW",
        "ts": "1618368350.045400",
        "team": "TKS1Q2JUE",
        "user_team": "TKS1Q2JUE",
        "source_team": "TKS1Q2JUE",
        "user_profile": {
            "avatar_hash": "0620fad631b1",
            "image_72": "https:\/\/avatars.slack-edge.com\/2019-11-04\/822570536406_0620fad631b132a16d69_72.png",
            "first_name": "s1260220",
            "real_name": "s1260220 Sukegawa",
            "display_name": "sukegawa",
            "team": "TKS1Q2JUE",
            "name": "s1260220",
            "is_restricted": false,
            "is_ultra_restricted": false
        },
        "blocks": [
            {
                "type": "rich_text",
                "block_id": "LdpCU",
                "elements": [
                    {
                        "type": "rich_text_section",
                        "elements": [
                            {
                                "type": "text",
                                "text": "ありがとー"
                            }
                        ]
                    }
                ]
            }
        ],
        "thread_ts": "1618363887.044300",
        "parent_user_id": "U01EVRBP38C"
    },
    {
        "type": "message",
        "text": "キノコ収穫",
        "files": [
            {
                "id": "F01U85S3AHY",
                "created": 1618370349,
                "timestamp": 1618370349,
                "name": "iOS の画像.jpg",
                "title": "iOS の画像",
                "mimetype": "image\/jpeg",
                "filetype": "jpg",
                "pretty_type": "JPEG",
                "user": "U01EVRBP38C",
                "editable": false,
                "size": 710783,
                "mode": "hosted",
                "is_external": false,
                "external_type": "",
                "is_public": true,
                "public_url_shared": false,
                "display_as_bot": false,
                "username": "",
                "url_private": "https:\/\/files.slack.com\/files-pri\/TKS1Q2JUE-F01U85S3AHY\/ios__________.jpg?t=xoxe-672058086966-2523672994084-2517456103667-564347be5337331371fc88513b8caa70",
                "url_private_download": "https:\/\/files.slack.com\/files-pri\/TKS1Q2JUE-F01U85S3AHY\/download\/ios__________.jpg?t=xoxe-672058086966-2523672994084-2517456103667-564347be5337331371fc88513b8caa70",
                "media_display_type": "unknown",
                "thumb_64": "https:\/\/files.slack.com\/files-tmb\/TKS1Q2JUE-F01U85S3AHY-2f2cea959b\/ios___________64.jpg?t=xoxe-672058086966-2523672994084-2517456103667-564347be5337331371fc88513b8caa70",
                "thumb_80": "https:\/\/files.slack.com\/files-tmb\/TKS1Q2JUE-F01U85S3AHY-2f2cea959b\/ios___________80.jpg?t=xoxe-672058086966-2523672994084-2517456103667-564347be5337331371fc88513b8caa70",
                "thumb_360": "https:\/\/files.slack.com\/files-tmb\/TKS1Q2JUE-F01U85S3AHY-2f2cea959b\/ios___________360.jpg?t=xoxe-672058086966-2523672994084-2517456103667-564347be5337331371fc88513b8caa70",
                "thumb_360_w": 270,
                "thumb_360_h": 360,
                "thumb_480": "https:\/\/files.slack.com\/files-tmb\/TKS1Q2JUE-F01U85S3AHY-2f2cea959b\/ios___________480.jpg?t=xoxe-672058086966-2523672994084-2517456103667-564347be5337331371fc88513b8caa70",
                "thumb_480_w": 360,
                "thumb_480_h": 480,
                "thumb_160": "https:\/\/files.slack.com\/files-tmb\/TKS1Q2JUE-F01U85S3AHY-2f2cea959b\/ios___________160.jpg?t=xoxe-672058086966-2523672994084-2517456103667-564347be5337331371fc88513b8caa70",
                "thumb_720": "https:\/\/files.slack.com\/files-tmb\/TKS1Q2JUE-F01U85S3AHY-2f2cea959b\/ios___________720.jpg?t=xoxe-672058086966-2523672994084-2517456103667-564347be5337331371fc88513b8caa70",
                "thumb_720_w": 540,
                "thumb_720_h": 720,
                "thumb_800": "https:\/\/files.slack.com\/files-tmb\/TKS1Q2JUE-F01U85S3AHY-2f2cea959b\/ios___________800.jpg?t=xoxe-672058086966-2523672994084-2517456103667-564347be5337331371fc88513b8caa70",
                "thumb_800_w": 800,
                "thumb_800_h": 1067,
                "thumb_960": "https:\/\/files.slack.com\/files-tmb\/TKS1Q2JUE-F01U85S3AHY-2f2cea959b\/ios___________960.jpg?t=xoxe-672058086966-2523672994084-2517456103667-564347be5337331371fc88513b8caa70",
                "thumb_960_w": 720,
                "thumb_960_h": 960,
                "thumb_1024": "https:\/\/files.slack.com\/files-tmb\/TKS1Q2JUE-F01U85S3AHY-2f2cea959b\/ios___________1024.jpg?t=xoxe-672058086966-2523672994084-2517456103667-564347be5337331371fc88513b8caa70",
                "thumb_1024_w": 768,
                "thumb_1024_h": 1024,
                "original_w": 3024,
                "original_h": 4032,
                "thumb_tiny": "AwAwACS0FBzyfzpdqnHX86Z5hHpxSCcEZBHFAEjKAhPfFR44FM85hu3NwenHFOVywyMflQBIF460u33FML46n9KTzPf9KAI2JMZGcfWq6hgmAwYUryb8xrnOMk+lRGVgu1jnHekxoeJAclmyQMVPbk7Nx4B6CqYwWxjPNXoIvLHznII4AHSgGOODRxTHO1yM9KbvpiIoQEX370+WIYDd8dqrsWD7QTipoy23Jb2waQxiKA2WOatiXJyeFA5queCTimSbip5oCw5nLMT6mk3VEh+X5sk\/WnZH+1+dAH\/\/2Q==",
                "permalink": "https:\/\/css-uoa.slack.com\/files\/U01EVRBP38C\/F01U85S3AHY\/ios__________.jpg",
                "permalink_public": "https:\/\/slack-files.com\/TKS1Q2JUE-F01U85S3AHY-c42c141070",
                "is_starred": false,
                "has_rich_preview": false
            },
            {
                "id": "F01U85S3FBL",
                "created": 1618370349,
                "timestamp": 1618370349,
                "name": "iOS の画像.jpg",
                "title": "iOS の画像",
                "mimetype": "image\/jpeg",
                "filetype": "jpg",
                "pretty_type": "JPEG",
                "user": "U01EVRBP38C",
                "editable": false,
                "size": 684798,
                "mode": "hosted",
                "is_external": false,
                "external_type": "",
                "is_public": true,
                "public_url_shared": false,
                "display_as_bot": false,
                "username": "",
                "url_private": "https:\/\/files.slack.com\/files-pri\/TKS1Q2JUE-F01U85S3FBL\/ios__________.jpg?t=xoxe-672058086966-2523672994084-2517456103667-564347be5337331371fc88513b8caa70",
                "url_private_download": "https:\/\/files.slack.com\/files-pri\/TKS1Q2JUE-F01U85S3FBL\/download\/ios__________.jpg?t=xoxe-672058086966-2523672994084-2517456103667-564347be5337331371fc88513b8caa70",
                "media_display_type": "unknown",
                "thumb_64": "https:\/\/files.slack.com\/files-tmb\/TKS1Q2JUE-F01U85S3FBL-7427fbcfc7\/ios___________64.jpg?t=xoxe-672058086966-2523672994084-2517456103667-564347be5337331371fc88513b8caa70",
                "thumb_80": "https:\/\/files.slack.com\/files-tmb\/TKS1Q2JUE-F01U85S3FBL-7427fbcfc7\/ios___________80.jpg?t=xoxe-672058086966-2523672994084-2517456103667-564347be5337331371fc88513b8caa70",
                "thumb_360": "https:\/\/files.slack.com\/files-tmb\/TKS1Q2JUE-F01U85S3FBL-7427fbcfc7\/ios___________360.jpg?t=xoxe-672058086966-2523672994084-2517456103667-564347be5337331371fc88513b8caa70",
                "thumb_360_w": 270,
                "thumb_360_h": 360,
                "thumb_480": "https:\/\/files.slack.com\/files-tmb\/TKS1Q2JUE-F01U85S3FBL-7427fbcfc7\/ios___________480.jpg?t=xoxe-672058086966-2523672994084-2517456103667-564347be5337331371fc88513b8caa70",
                "thumb_480_w": 360,
                "thumb_480_h": 480,
                "thumb_160": "https:\/\/files.slack.com\/files-tmb\/TKS1Q2JUE-F01U85S3FBL-7427fbcfc7\/ios___________160.jpg?t=xoxe-672058086966-2523672994084-2517456103667-564347be5337331371fc88513b8caa70",
                "thumb_720": "https:\/\/files.slack.com\/files-tmb\/TKS1Q2JUE-F01U85S3FBL-7427fbcfc7\/ios___________720.jpg?t=xoxe-672058086966-2523672994084-2517456103667-564347be5337331371fc88513b8caa70",
                "thumb_720_w": 540,
                "thumb_720_h": 720,
                "thumb_800": "https:\/\/files.slack.com\/files-tmb\/TKS1Q2JUE-F01U85S3FBL-7427fbcfc7\/ios___________800.jpg?t=xoxe-672058086966-2523672994084-2517456103667-564347be5337331371fc88513b8caa70",
                "thumb_800_w": 800,
                "thumb_800_h": 1067,
                "thumb_960": "https:\/\/files.slack.com\/files-tmb\/TKS1Q2JUE-F01U85S3FBL-7427fbcfc7\/ios___________960.jpg?t=xoxe-672058086966-2523672994084-2517456103667-564347be5337331371fc88513b8caa70",
                "thumb_960_w": 720,
                "thumb_960_h": 960,
                "thumb_1024": "https:\/\/files.slack.com\/files-tmb\/TKS1Q2JUE-F01U85S3FBL-7427fbcfc7\/ios___________1024.jpg?t=xoxe-672058086966-2523672994084-2517456103667-564347be5337331371fc88513b8caa70",
                "thumb_1024_w": 768,
                "thumb_1024_h": 1024,
                "original_w": 3024,
                "original_h": 4032,
                "thumb_tiny": "AwAwACS7IygEZqNpQynqM96imyANqk49DVVJV2MrMeT37UmMsxSFQyAsSec0jTEqRuJ\/DFQLOqnKnpx0pHOcHcMEZpDHMjSnJI445NJ5B9R+dSIyogXYre5pfNT\/AJ5L+dVoSSBv3xHbbUAEcchVxj0PY1Mjf6U59AKSVcPKWAKEYHtSY0Rq6l9rMoX0A61HJgtknIqMwqeVbip7UBZC3XAxzSGSR2TFQd5\/CnfYW\/vmnPuZsqcD0pu1\/wC8aYiOM5nlPvSu3UGoYCfmLdSc05zmmIc0IAxyDQqle3HpTUmbaVxn3oYsaQyQzbcDrj0o8\/6\/lUABI6UuDSuOx\/\/Z",
                "permalink": "https:\/\/css-uoa.slack.com\/files\/U01EVRBP38C\/F01U85S3FBL\/ios__________.jpg",
                "permalink_public": "https:\/\/slack-files.com\/TKS1Q2JUE-F01U85S3FBL-f5bfa7cc42",
                "is_starred": false,
                "has_rich_preview": false
            }
        ],
        "upload": false,
        "blocks": [
            {
                "type": "rich_text",
                "block_id": "HQB",
                "elements": [
                    {
                        "type": "rich_text_section",
                        "elements": [
                            {
                                "type": "text",
                                "text": "キノコ収穫"
                            }
                        ]
                    }
                ]
            }
        ],
        "user": "U01EVRBP38C",
        "ts": "1618370385.046300",
        "client_msg_id": "9B3878FF-299C-41B6-91B5-1061658CA9A5",
        "thread_ts": "1618370385.046300",
        "reply_count": 7,
        "reply_users_count": 5,
        "latest_reply": "1618371395.051400",
        "reply_users": [
            "UKS1Q2KTQ",
            "U01EL0SAUTF",
            "UKH07E67M",
            "U01EVRBP38C",
            "U01F42ZFA73"
        ],
        "replies": [
            {
                "user": "UKS1Q2KTQ",
                "ts": "1618370573.046900"
            },
            {
                "user": "U01EL0SAUTF",
                "ts": "1618370662.047200"
            },
            {
                "user": "UKH07E67M",
                "ts": "1618370678.047500"
            },
            {
                "user": "U01EVRBP38C",
                "ts": "1618370928.049400"
            },
            {
                "user": "U01F42ZFA73",
                "ts": "1618371168.050300"
            },
            {
                "user": "U01EVRBP38C",
                "ts": "1618371375.050700"
            },
            {
                "user": "U01EVRBP38C",
                "ts": "1618371395.051400"
            }
        ],
        "is_locked": false,
        "subscribed": true,
        "last_read": "1618371395.051400",
        "reactions": [
            {
                "name": "clap",
                "users": [
                    "UQ47R82RW"
                ],
                "count": 1
            },
            {
                "name": "tada",
                "users": [
                    "U01EL0SAUTF"
                ],
                "count": 1
            },
            {
                "name": "mushroom",
                "users": [
                    "UKH07E67M",
                    "U01FP2RDV44",
                    "UKUKA65GU",
                    "UPSPAP97D"
                ],
                "count": 4
            }
        ]
    },
    {
        "client_msg_id": "ce239256-132e-489e-865b-622a3769cf44",
        "type": "message",
        "text": "amazon で売ってるやつ？",
        "user": "UKS1Q2KTQ",
        "ts": "1618370573.046900",
        "team": "TKS1Q2JUE",
        "user_team": "TKS1Q2JUE",
        "source_team": "TKS1Q2JUE",
        "user_profile": {
            "avatar_hash": "g2cdaa6f0a3e",
            "image_72": "https:\/\/secure.gravatar.com\/avatar\/72cdaa6f0a3e75d134cc6b97d821b078.jpg?s=72&d=https%3A%2F%2Fa.slack-edge.com%2Fdf10d%2Fimg%2Favatars%2Fava_0003-72.png",
            "first_name": "Yasuhiro",
            "real_name": "Yasuhiro Hashimoto",
            "display_name": "hashimoto",
            "team": "TKS1Q2JUE",
            "name": "yasuhirohashimoto",
            "is_restricted": false,
            "is_ultra_restricted": false
        },
        "blocks": [
            {
                "type": "rich_text",
                "block_id": "Lx5v",
                "elements": [
                    {
                        "type": "rich_text_section",
                        "elements": [
                            {
                                "type": "text",
                                "text": "amazon で売ってるやつ？"
                            }
                        ]
                    }
                ]
            }
        ],
        "thread_ts": "1618370385.046300",
        "parent_user_id": "U01EVRBP38C"
    },
    {
        "client_msg_id": "368ce368-43a8-4303-95d8-6812077bb4d8",
        "type": "message",
        "text": "めちゃ美味しそう！！！",
        "user": "U01EL0SAUTF",
        "ts": "1618370662.047200",
        "team": "TKS1Q2JUE",
        "user_team": "TKS1Q2JUE",
        "source_team": "TKS1Q2JUE",
        "user_profile": {
            "avatar_hash": "97f546e52313",
            "image_72": "https:\/\/avatars.slack-edge.com\/2020-11-13\/1499146897842_97f546e523132e359093_72.png",
            "first_name": "Honda",
            "real_name": "Honda Daiki",
            "display_name": "daiki",
            "team": "TKS1Q2JUE",
            "name": "s1270123",
            "is_restricted": false,
            "is_ultra_restricted": false
        },
        "blocks": [
            {
                "type": "rich_text",
                "block_id": "LTS",
                "elements": [
                    {
                        "type": "rich_text_section",
                        "elements": [
                            {
                                "type": "text",
                                "text": "めちゃ美味しそう！！！"
                            }
                        ]
                    }
                ]
            }
        ],
        "thread_ts": "1618370385.046300",
        "parent_user_id": "U01EVRBP38C"
    },
    {
        "client_msg_id": "4424F08C-5FE3-45D9-9D8B-F140A93792C5",
        "type": "message",
        "text": "えすご",
        "user": "UKH07E67M",
        "ts": "1618370678.047500",
        "team": "TKS1Q2JUE",
        "user_team": "TKS1Q2JUE",
        "source_team": "TKS1Q2JUE",
        "user_profile": {
            "avatar_hash": "42b0524c15ef",
            "image_72": "https:\/\/avatars.slack-edge.com\/2020-12-22\/1589400144565_42b0524c15efa13345bf_72.png",
            "first_name": "Aoshi",
            "real_name": "Aoshi Suzuki",
            "display_name": "aoshi",
            "team": "TKS1Q2JUE",
            "name": "s1260241",
            "is_restricted": false,
            "is_ultra_restricted": false
        },
        "blocks": [
            {
                "type": "rich_text",
                "block_id": "4pR",
                "elements": [
                    {
                        "type": "rich_text_section",
                        "elements": [
                            {
                                "type": "text",
                                "text": "えすご"
                            }
                        ]
                    }
                ]
            }
        ],
        "thread_ts": "1618370385.046300",
        "parent_user_id": "U01EVRBP38C"
    },
    {
        "client_msg_id": "73214C09-4B4E-489A-9A0C-9BA0AC6E1609",
        "type": "message",
        "text": "<@UKS1Q2KTQ> \ndaikiからの誕生日プレゼントでもらったキノコ栽培キットです！",
        "user": "U01EVRBP38C",
        "ts": "1618370928.049400",
        "team": "TKS1Q2JUE",
        "user_team": "TKS1Q2JUE",
        "source_team": "TKS1Q2JUE",
        "user_profile": {
            "avatar_hash": "1d491b4b6d33",
            "image_72": "https:\/\/avatars.slack-edge.com\/2020-11-14\/1513053597985_1d491b4b6d33b99610d3_72.png",
            "first_name": "Masashi",
            "real_name": "Masashi Sakurai",
            "display_name": "sakurai",
            "team": "TKS1Q2JUE",
            "name": "s12701350406",
            "is_restricted": false,
            "is_ultra_restricted": false
        },
        "blocks": [
            {
                "type": "rich_text",
                "block_id": "G6Jl",
                "elements": [
                    {
                        "type": "rich_text_section",
                        "elements": [
                            {
                                "type": "user",
                                "user_id": "UKS1Q2KTQ"
                            },
                            {
                                "type": "text",
                                "text": " \ndaikiからの誕生日プレゼントでもらったキノコ栽培キットです！"
                            }
                        ]
                    }
                ]
            }
        ],
        "thread_ts": "1618370385.046300",
        "parent_user_id": "U01EVRBP38C",
        "reactions": [
            {
                "name": "laughing",
                "users": [
                    "UKS1Q2KTQ"
                ],
                "count": 1
            },
            {
                "name": "pleading_face",
                "users": [
                    "U01EL0SAUTF"
                ],
                "count": 1
            }
        ]
    },
    {
        "client_msg_id": "DBCBC5C8-D27A-4681-A09F-0CF59C9EF1C9",
        "type": "message",
        "text": "結構、早く育つんだな",
        "user": "U01F42ZFA73",
        "ts": "1618371168.050300",
        "team": "TKS1Q2JUE",
        "user_team": "TKS1Q2JUE",
        "source_team": "TKS1Q2JUE",
        "user_profile": {
            "avatar_hash": "fff11f0294e9",
            "image_72": "https:\/\/avatars.slack-edge.com\/2020-11-14\/1507642753412_fff11f0294e9009f9878_72.png",
            "first_name": "Hayashi",
            "real_name": "Hayashi Ren",
            "display_name": "ren",
            "team": "TKS1Q2JUE",
            "name": "s1270247",
            "is_restricted": false,
            "is_ultra_restricted": false
        },
        "blocks": [
            {
                "type": "rich_text",
                "block_id": "s1q",
                "elements": [
                    {
                        "type": "rich_text_section",
                        "elements": [
                            {
                                "type": "text",
                                "text": "結構、早く育つんだな"
                            }
                        ]
                    }
                ]
            }
        ],
        "thread_ts": "1618370385.046300",
        "parent_user_id": "U01EVRBP38C"
    },
    {
        "client_msg_id": "962BE843-7FBE-4653-997A-C5D3DB824FDA",
        "type": "message",
        "text": "かなり早い笑笑",
        "user": "U01EVRBP38C",
        "ts": "1618371375.050700",
        "team": "TKS1Q2JUE",
        "user_team": "TKS1Q2JUE",
        "source_team": "TKS1Q2JUE",
        "user_profile": {
            "avatar_hash": "1d491b4b6d33",
            "image_72": "https:\/\/avatars.slack-edge.com\/2020-11-14\/1513053597985_1d491b4b6d33b99610d3_72.png",
            "first_name": "Masashi",
            "real_name": "Masashi Sakurai",
            "display_name": "sakurai",
            "team": "TKS1Q2JUE",
            "name": "s12701350406",
            "is_restricted": false,
            "is_ultra_restricted": false
        },
        "blocks": [
            {
                "type": "rich_text",
                "block_id": "fS3Ez",
                "elements": [
                    {
                        "type": "rich_text_section",
                        "elements": [
                            {
                                "type": "text",
                                "text": "かなり早い笑笑"
                            }
                        ]
                    }
                ]
            }
        ],
        "thread_ts": "1618370385.046300",
        "parent_user_id": "U01EVRBP38C"
    },
    {
        "client_msg_id": "FDFB3F11-E1EB-4DD3-8DAF-4B23801934FE",
        "type": "message",
        "text": "はよ食ってくれと言わんばかりの早さ笑笑",
        "user": "U01EVRBP38C",
        "ts": "1618371395.051400",
        "team": "TKS1Q2JUE",
        "user_team": "TKS1Q2JUE",
        "source_team": "TKS1Q2JUE",
        "user_profile": {
            "avatar_hash": "1d491b4b6d33",
            "image_72": "https:\/\/avatars.slack-edge.com\/2020-11-14\/1513053597985_1d491b4b6d33b99610d3_72.png",
            "first_name": "Masashi",
            "real_name": "Masashi Sakurai",
            "display_name": "sakurai",
            "team": "TKS1Q2JUE",
            "name": "s12701350406",
            "is_restricted": false,
            "is_ultra_restricted": false
        },
        "blocks": [
            {
                "type": "rich_text",
                "block_id": "D8q",
                "elements": [
                    {
                        "type": "rich_text_section",
                        "elements": [
                            {
                                "type": "text",
                                "text": "はよ食ってくれと言わんばかりの早さ笑笑"
                            }
                        ]
                    }
                ]
            }
        ],
        "thread_ts": "1618370385.046300",
        "parent_user_id": "U01EVRBP38C",
        "reactions": [
            {
                "name": "star-struck",
                "users": [
                    "U01EL0SAUTF",
                    "U01EP8BUKQT"
                ],
                "count": 2
            }
        ]
    }
]